predikto/__init__.py
predikto/auth.py
predikto/client.py
predikto/errors.py
predikto/tools.py
predikto/resources/__init__.py
predikto/resources/base.py
predikto/resources/prediktor.py
predikto/resources/project.py
predikto/resources/report.py
predikto/resources/status.py
predikto/resources/upload.py
predikto/resources/workspace.py
predikto-1.2.0.dist-info/DESCRIPTION.rst
predikto-1.2.0.dist-info/METADATA
predikto-1.2.0.dist-info/metadata.json
predikto-1.2.0.dist-info/RECORD
predikto-1.2.0.dist-info/top_level.txt
predikto-1.2.0.dist-info/WHEEL
