Metadata-Version: 2.0
Name: predikto
Version: 1.2.0
Summary: Predikto Python SDK
Home-page: https://github.com/predikto/python-sdk
Author: Predikto, Inc.
Author-email: rrusso@predikto.com
License: ASL
Download-URL: https://github.com/predikto/python-sdk/tarball/1.1.0
Keywords: predikto,analytics,predictive
Platform: UNKNOWN
Classifier: Development Status :: 5 - Production/Stable
Classifier: Intended Audience :: Developers
Classifier: Natural Language :: English
Classifier: License :: OSI Approved :: Apache Software License
Classifier: Operating System :: OS Independent
Classifier: Programming Language :: Python
Classifier: Programming Language :: Python :: 3
Classifier: Programming Language :: Python :: 3.3
Classifier: Programming Language :: Python :: 3.4
Classifier: Topic :: Scientific/Engineering :: Information Analysis
